MANIFEST.in
README.rst
setup.py
Python_buildtest_config.egg-info/PKG-INFO
Python_buildtest_config.egg-info/SOURCES.txt
Python_buildtest_config.egg-info/dependency_links.txt
Python_buildtest_config.egg-info/requires.txt
Python_buildtest_config.egg-info/top_level.txt
buildtest/__init__.py
buildtest/python/code/Babel/conftest.py
buildtest/python/code/Babel/reference.txt
buildtest/python/code/Babel/test_core.py
buildtest/python/code/Babel/test_date_intervals.py
buildtest/python/code/Babel/test_dates.py
buildtest/python/code/Babel/test_day_periods.py
buildtest/python/code/Babel/test_languages.py
buildtest/python/code/Babel/test_lists.py
buildtest/python/code/Babel/test_localedata.py
buildtest/python/code/Babel/test_numbers.py
buildtest/python/code/Babel/test_plural.py
buildtest/python/code/Babel/test_smoke.py
buildtest/python/code/Babel/test_support.py
buildtest/python/code/Babel/test_util.py
buildtest/python/code/Bottleneck/basic_bottleneck.py
buildtest/python/code/Bottleneck/reference.txt
buildtest/python/code/Cython/fib.pyx
buildtest/python/code/Cython/fibtest.py
buildtest/python/code/Cython/setup.py
buildtest/python/code/anaconda-client/anaconda_search.py
buildtest/python/code/anaconda-client/anaconda_show.py
buildtest/python/code/anaconda-client/anaconda_whoami.py
buildtest/python/code/astriod/reference.txt
buildtest/python/code/astriod/resources.py
buildtest/python/code/astriod/unittest_brain.py
buildtest/python/code/astriod/unittest_builder.py
buildtest/python/code/astriod/unittest_helpers.py
buildtest/python/code/astriod/unittest_inference.py
buildtest/python/code/astriod/unittest_lookup.py
buildtest/python/code/astriod/unittest_manager.py
buildtest/python/code/astriod/unittest_modutils.py
buildtest/python/code/astriod/unittest_nodes.py
buildtest/python/code/astriod/unittest_object_model.py
buildtest/python/code/astriod/unittest_objects.py
buildtest/python/code/astriod/unittest_peephole.py
buildtest/python/code/astriod/unittest_peephole.pyc
buildtest/python/code/astriod/unittest_protocols.py
buildtest/python/code/astriod/unittest_python3.py
buildtest/python/code/astriod/unittest_raw_building.py
buildtest/python/code/astriod/unittest_regrtest.py
